hart/__init__.py
hart/args/__init__.py
hart/args/clm_args.py
hart/args/ft_args.py
hart/data/__init__.py
hart/data/data_collator.py
hart/data/data_utils/__init__.py
hart/data/data_utils/utils_gpt2hlc/clm_data_utils.py
hart/data/data_utils/utils_gpt2hlc/ft_user_data_utils_gpt2hlc.py
hart/data/data_utils/utils_gpt2hlc_wrapper/continue_pretrain_data_utils.py
hart/data/data_utils/utils_hart/ft_doc_data_utils.py
hart/data/data_utils/utils_hart/ft_doc_disable_hulm_batching_data_utils.py
hart/data/data_utils/utils_hart/ft_user_data_utils.py
hart/data/data_utils/utils_hart/hulm_data_utils.py
hart/data/data_utils/utils_hart/utils_optuna_trials/hulm_sample_data_utils.py
hart/data/data_utils/utils_hart_wrapper/__init__.py
hart/data/data_utils/utils_hart_wrapper/continue_pretrain_hulm_data_utils_one_doc_per_block.py
hart/data/data_utils/utils_hart_wrapper/continue_pretrain_hulm_data_utis.py
hart/data/data_utils/utils_hart_wrapper/finetune_document_classify_data_utils.py
hart/data/data_utils/utils_hart_wrapper/finetune_user_regression_data_utils.py
hart/data/data_utils/utils_hart_wrapper/inference_data_utils.py
hart/data/data_utils/utils_hart_wrapper/inference_data_utils_one_doc_per_block.py
hart/data/initial_history/__init__.py
hart/data/initial_history/initialized_history_tensor.pt
hart/data/initial_history/initialized_history_tensor_torch14.pt
hart/examples/__init__.py
hart/examples/gpt2hlc/run_clm_gpt2.py
hart/examples/gpt2hlc/run_ft_gpt2hlc.py
hart/examples/gpt2hlc_wrapper/run_continue_pt_gpt_twt.py
hart/examples/hart/__init__.py
hart/examples/hart/run_ft_hart.py
hart/examples/hart/run_hulm_hart.py
hart/examples/hart_wrapper/__init__.py
hart/examples/hart_wrapper/get_hart_embeddings.py
hart/examples/hart_wrapper/get_hart_embeddings_one_doc_per_block.py
hart/examples/hart_wrapper/run_continue_pt_hart.py
hart/examples/hart_wrapper/run_continue_pt_hart_one_doc_per_block.py
hart/examples/hart_wrapper/run_finetune_hart.py
hart/examples/optuna_trials/run_ft_gpt2hlc_trials.py
hart_wrapper-1.0.dist-info/licenses/LICENSE
hart_wrapper-1.0.dist-info/licenses/LICENSE copy
hart_wrapper-1.0.dist-info/METADATA
hart_wrapper-1.0.dist-info/WHEEL
hart_wrapper-1.0.dist-info/top_level.txt
hart_wrapper-1.0.dist-info/RECORD
